LICENSE
MANIFEST.in
README.md
setup.cfg
setup.py
django_paperlayer/manage.py
django_paperlayer.egg-info/PKG-INFO
django_paperlayer.egg-info/SOURCES.txt
django_paperlayer.egg-info/dependency_links.txt
django_paperlayer.egg-info/requires.txt
django_paperlayer.egg-info/top_level.txt
django_paperlayer/api/__init__.py
django_paperlayer/api/admin.py
django_paperlayer/api/apps.py
django_paperlayer/api/mail.py
django_paperlayer/api/permission.py
django_paperlayer/api/tests.py
django_paperlayer/api/urls.py
django_paperlayer/api/utils.py
django_paperlayer/api/migrations/0001_initial.py
django_paperlayer/api/migrations/0002_auto_20201204_1708.py
django_paperlayer/api/migrations/0002_collaborationrequest.py
django_paperlayer/api/migrations/0003_auto_20201206_1712.py
django_paperlayer/api/migrations/0004_merge_20201206_1815.py
django_paperlayer/api/migrations/0005_auto_20201206_2024.py
django_paperlayer/api/migrations/0006_auto_20201206_2025.py
django_paperlayer/api/migrations/0007_auto_20201206_2026.py
django_paperlayer/api/migrations/0008_auto_20201206_2028.py
django_paperlayer/api/migrations/0009_auto_20201208_2042.py
django_paperlayer/api/migrations/0009_auto_20201209_1436.py
django_paperlayer/api/migrations/0009_auto_20201212_1633.py
django_paperlayer/api/migrations/0010_auto_20201212_1717.py
django_paperlayer/api/migrations/0010_merge_20201214_2048.py
django_paperlayer/api/migrations/0011_auto_20201214_2048.py
django_paperlayer/api/migrations/0012_auto_20201215_1844.py
django_paperlayer/api/migrations/0013_merge_20201215_2314.py
django_paperlayer/api/migrations/0014_auto_20201217_1125.py
django_paperlayer/api/migrations/0015_auto_20201219_1124.py
django_paperlayer/api/migrations/0015_publication.py
django_paperlayer/api/migrations/0016_auto_20201221_2047.py
django_paperlayer/api/migrations/0016_auto_20201221_2147.py
django_paperlayer/api/migrations/0016_auto_20210117_1657.py
django_paperlayer/api/migrations/0017_auto_20201228_1217.py
django_paperlayer/api/migrations/0018_merge_20210107_2115.py
django_paperlayer/api/migrations/0019_auto_20210117_1056.py
django_paperlayer/api/migrations/0020_auto_20210117_1512.py
django_paperlayer/api/migrations/0020_merge_20210117_1732.py
