Metadata-Version: 2.1
Name: django-paperlayer
Version: 1.7
Summary: An simple academic platform
Home-page: https://github.com/bounswe/bounswe2020group3
Author: Paperlayer Dev Team
Author-email: bounswe2020group3@gmail.com
License: MIT License
Download-URL: https://github.com/bounswe/bounswe2020group3/archive/2.2.1.tar.gz
Platform: UNKNOWN
Classifier: Development Status :: 3 - Alpha
Classifier: Intended Audience :: Developers
Classifier: Topic :: Software Development :: Build Tools
Classifier: License :: OSI Approved :: MIT License
Classifier: Programming Language :: Python :: 3.9
Requires-Python: >=3.6
